pywaybiller/__init__.py
pywaybiller/apis.py
pywaybiller/client.py
pywaybiller/docs/BlankEnum.md
pywaybiller/docs/DestinationsApi.md
pywaybiller/docs/DestinationsList403Response.md
pywaybiller/docs/EmploymentsApi.md
pywaybiller/docs/EmploymentsRetrieve404Response.md
pywaybiller/docs/ExternalAPIDestination.md
pywaybiller/docs/ExternalAPIDestinationRawData.md
pywaybiller/docs/ExternalAPIEmployment.md
pywaybiller/docs/ExternalAPIHoldingBase.md
pywaybiller/docs/ExternalAPIHoldingBasePreviousOwner.md
pywaybiller/docs/ExternalAPIHoldingBasePreviousOwnerRequest.md
pywaybiller/docs/ExternalAPIHoldingBaseRequest.md
pywaybiller/docs/ExternalAPILoaderActionLog.md
pywaybiller/docs/ExternalAPILoaderActionLogComment.md
pywaybiller/docs/ExternalAPILoaderActionLogRawData.md
pywaybiller/docs/ExternalAPIOrder.md
pywaybiller/docs/ExternalAPIOrderCreate.md
pywaybiller/docs/ExternalAPIOrderCreateRequest.md
pywaybiller/docs/ExternalAPIOrderList.md
pywaybiller/docs/ExternalAPIOrderOrigin.md
pywaybiller/docs/ExternalAPIOrderOriginRequest.md
pywaybiller/docs/ExternalAPIOrderOriginsAssortments.md
pywaybiller/docs/ExternalAPIOrderOriginsAssortmentsRequest.md
pywaybiller/docs/ExternalAPIOrderRawData.md
pywaybiller/docs/ExternalAPIOrderTransportCompanies.md
pywaybiller/docs/ExternalAPIOrderTransportCompaniesRequest.md
pywaybiller/docs/ExternalAPIOrderUpdate.md
pywaybiller/docs/ExternalAPIOrderUpdateRequest.md
pywaybiller/docs/ExternalAPIOrderVehicles.md
pywaybiller/docs/ExternalAPIOrderVehiclesRequest.md
pywaybiller/docs/ExternalAPIOriginAssortment.md
pywaybiller/docs/ExternalAPIOriginAssortmentRawData.md
pywaybiller/docs/ExternalAPIOriginAssortmentRequest.md
pywaybiller/docs/ExternalAPIOriginCreate.md
pywaybiller/docs/ExternalAPIOriginCreateRequest.md
pywaybiller/docs/ExternalAPIOriginCreateWaybillCreatedEmailsLanguage.md
pywaybiller/docs/ExternalAPIOriginList.md
pywaybiller/docs/ExternalAPIOriginLocation.md
pywaybiller/docs/ExternalAPIOriginLocationRequest.md
pywaybiller-0.2.1.dist-info/LICENSE
pywaybiller-0.2.1.dist-info/METADATA
pywaybiller-0.2.1.dist-info/WHEEL
pywaybiller-0.2.1.dist-info/RECORD
