Metadata-Version: 2.3
Name: pywaybiller
Version: 0.2.1
Summary: Python client for waybiller.com external API
License: MIT
Keywords: OpenAPI,OpenAPI-Generator,pywaybiller
Author: Thorgate Digital
Author-email: software@thorgate.eu
Requires-Python: >=3.9,<4
Classifier: License :: OSI Approved :: MIT License
Classifier: Programming Language :: Python :: 3
Classifier: Programming Language :: Python :: 3.9
Classifier: Programming Language :: Python :: 3.10
Classifier: Programming Language :: Python :: 3.11
Classifier: Programming Language :: Python :: 3.12
Classifier: Programming Language :: Python :: 3.13
Requires-Dist: pydantic (>=2)
Requires-Dist: python-dateutil (>=2.8.2)
Requires-Dist: typing-extensions (>=4.7.1)
Requires-Dist: urllib3 (>=1.25.3,<3.0.0)
